channels_easy/__init__.py
channels_easy/generic.py
channels_easy/json.py
channels_easy-0.3.0.dist-info/LICENSE
channels_easy-0.3.0.dist-info/WHEEL
channels_easy-0.3.0.dist-info/METADATA
channels_easy-0.3.0.dist-info/RECORD
