Metadata-Version: 2.1
Name: channels-easy
Version: 0.3.0
Summary: A thin wrapper around channels consumer to make things EASY
Home-page: https://namantam1.github.io/channels-easy
License: MIT
Keywords: channels,django,websocket
Author: Naman Tamrakar
Author-email: namantam1@gmail.com
Requires-Python: >=3.7,<4.0
Classifier: License :: OSI Approved :: MIT License
Classifier: Programming Language :: Python :: 3
Classifier: Programming Language :: Python :: 3.10
Classifier: Programming Language :: Python :: 3.7
Classifier: Programming Language :: Python :: 3.8
Classifier: Programming Language :: Python :: 3.9
Requires-Dist: Django (>=3.0)
Requires-Dist: channels (>=3.0)
Project-URL: Repository, https://github.com/namantam1/channels-easy
